infura/__init__.py
infura/infura.py
infura-0.2.1.dist-info/LICENSE
infura-0.2.1.dist-info/METADATA
infura-0.2.1.dist-info/WHEEL
infura-0.2.1.dist-info/top_level.txt
infura-0.2.1.dist-info/RECORD
