Metadata-Version: 2.1
Name: infura
Version: 0.2.1
Summary: Infura.io wrapper
Home-page: https://github.com/neoctobers/infura
Author: @neoctobers
Author-email: neoctobers@gmail.com
License: UNKNOWN
Platform: UNKNOWN
Classifier: Programming Language :: Python :: 3
Classifier: License :: OSI Approved :: MIT License
Classifier: Operating System :: OS Independent
Requires-Dist: requests-cache
